configurence/__init__.py
configurence/py.typed
configurence-2.0.3.dist-info/METADATA
configurence-2.0.3.dist-info/WHEEL
configurence-2.0.3.dist-info/entry_points.txt
configurence-2.0.3.dist-info/top_level.txt
configurence-2.0.3.dist-info/RECORD
