Metadata-Version: 2.2
Name: configurence
Version: 2.0.3
Summary: A simple CLI configuration library
Author-email: Josh Holbrook <josh.holbrook@gmail.com>
License: Apache-2.0
Requires-Python: >=3.11
Requires-Dist: appdirs
Requires-Dist: click
Requires-Dist: pyyaml
